{
  "updatedAt": 1782829103,
  "wallets": {
    "0x57f2819c959abbcf22623d5ec1d3164b213e9711": {
      "HYPE": {
        "side": "LONG",
        "szi": 3266.21,
        "lev": 10,
        "entry": 64.289,
        "mark": 65.85300000000001,
        "notional": 215089.72713,
        "uPnl": 5108.170492
      },
      "LIT": {
        "side": "LONG",
        "szi": 112848,
        "lev": 5,
        "entry": 1.747211,
        "mark": 1.9529,
        "notional": 220380.8592,
        "uPnl": 23211.5864
      }
    },
    "0x3705121529bf40d77e8e7b625120551b151d9af2": {
      "SOL": {
        "side": "LONG",
        "szi": 700,
        "lev": 5,
        "entry": 72.4277,
        "mark": 73.384,
        "notional": 51368.8,
        "uPnl": 669.379226
      },
      "HYPE": {
        "side": "LONG",
        "szi": 4500,
        "lev": 5,
        "entry": 61.9491,
        "mark": 65.853,
        "notional": 296338.5,
        "uPnl": 17567.344333
      },
      "PUMP": {
        "side": "LONG",
        "szi": 23000000,
        "lev": 5,
        "entry": 0.001428,
        "mark": 0.001409,
        "notional": 32407,
        "uPnl": -453
      }
    },
    "0xdd54150be70967523a256f92db193845acf58714": {},
    "0xc914267b2b98cabf20ef904de5fbb326c982855d": {
      "HYPE": {
        "side": "LONG",
        "szi": 1413.26,
        "lev": 10,
        "entry": 38.7688,
        "mark": 65.87,
        "notional": 93091.4362,
        "uPnl": 38301.036752
      }
    },
    "0x082e843a431aef031264dc232693dd710aedca88": {
      "HYPE": {
        "side": "LONG",
        "szi": 1380042.66,
        "lev": 5,
        "entry": 38.6755,
        "mark": 65.87,
        "notional": 90903410.0142,
        "uPnl": 37529479.967452
      }
    },
    "0x4e14fc11f58b64740e66e4b1aa188a4b007c0eab": {},
    "0x85530f0ff6496c72a619f37a60f3c1a59077737f": {},
    "0xe44bd27c9f10fa2f89fdb3ab4b4f0e460da29ea8": {}
  }
}
