{
  "updatedAt": 1780354968,
  "wallets": {
    "0x57f2819c959abbcf22623d5ec1d3164b213e9711": {
      "ETH": {
        "side": "LONG",
        "szi": 5000,
        "lev": 25,
        "entry": 1989.32,
        "mark": 2003.6,
        "notional": 10018000,
        "uPnl": 71385.21792
      },
      "HYPE": {
        "side": "LONG",
        "szi": 45000.69,
        "lev": 10,
        "entry": 59.6259,
        "mark": 74.053,
        "notional": 3332436.09657,
        "uPnl": 649228.92754
      }
    },
    "0x3705121529bf40d77e8e7b625120551b151d9af2": {
      "BTC": {
        "side": "LONG",
        "szi": 2.7,
        "lev": 5,
        "entry": 74214.5,
        "mark": 71366,
        "notional": 192688.2,
        "uPnl": -7691.13431
      },
      "NEAR": {
        "side": "LONG",
        "szi": 33333.3,
        "lev": 10,
        "entry": 2.34367,
        "mark": 2.6791,
        "notional": 89303.24403,
        "uPnl": 11180.66621
      },
      "HYPE": {
        "side": "LONG",
        "szi": 1700,
        "lev": 5,
        "entry": 50.2529,
        "mark": 74.048,
        "notional": 125881.6,
        "uPnl": 40451.520999
      },
      "ASTER": {
        "side": "LONG",
        "szi": 88888,
        "lev": 5,
        "entry": 0.735592,
        "mark": 0.69068,
        "notional": 61393.16384,
        "uPnl": -3992.214396
      }
    },
    "0xdd54150be70967523a256f92db193845acf58714": {
      "LIT": {
        "side": "LONG",
        "szi": 80000,
        "lev": 5,
        "entry": 1.341537,
        "mark": 1.3672,
        "notional": 109376,
        "uPnl": 2053.0024
      }
    },
    "0xc914267b2b98cabf20ef904de5fbb326c982855d": {
      "BTC": {
        "side": "LONG",
        "szi": 3.67304,
        "lev": 40,
        "entry": 74791.4,
        "mark": 71366,
        "notional": 262130.17264,
        "uPnl": -12581.9301
      },
      "ETH": {
        "side": "SHORT",
        "szi": -19.4555,
        "lev": 25,
        "entry": 2109.54,
        "mark": 2003.5,
        "notional": 38979.09425,
        "uPnl": 2063.10996
      },
      "SOL": {
        "side": "SHORT",
        "szi": -426.8,
        "lev": 20,
        "entry": 85.0398,
        "mark": 81.26799999999999,
        "notional": 34685.1824,
        "uPnl": 1609.839951
      },
      "JUP": {
        "side": "SHORT",
        "szi": -213579,
        "lev": 10,
        "entry": 0.185344,
        "mark": 0.19874999999999998,
        "notional": 42448.82625,
        "uPnl": -2863.20293
      },
      "TAO": {
        "side": "LONG",
        "szi": 172.223,
        "lev": 5,
        "entry": 272.544,
        "mark": 253.06999999999996,
        "notional": 43584.47461,
        "uPnl": -3353.984238
      },
      "ENA": {
        "side": "SHORT",
        "szi": -630231,
        "lev": 10,
        "entry": 0.102151,
        "mark": 0.088561,
        "notional": 55813.887591,
        "uPnl": 8565.104672
      },
      "PURR": {
        "side": "LONG",
        "szi": 310694,
        "lev": 3,
        "entry": 0.116536,
        "mark": 0.14246,
        "notional": 44261.46724,
        "uPnl": 8054.212201
      },
      "HYPE": {
        "side": "LONG",
        "szi": 4391.57,
        "lev": 10,
        "entry": 38.7688,
        "mark": 74.048,
        "notional": 325186.97536,
        "uPnl": 154931.06026
      },
      "FARTCOIN": {
        "side": "LONG",
        "szi": 215599.1,
        "lev": 10,
        "entry": 0.18557,
        "mark": 0.15324000000000002,
        "notional": 33038.406084,
        "uPnl": -6972.236836
      },
      "ZEC": {
        "side": "LONG",
        "szi": 299.77,
        "lev": 10,
        "entry": 426.4117,
        "mark": 545.94,
        "notional": 163656.4338,
        "uPnl": 35830.986659
      }
    }
  }
}
