{
  "baseline": {
    "BTC": 3.08,
    "XRP": 1.16,
    "ETH": 2.38,
    "ANSEM": 1.1,
    "SOL": 1.48,
    "SHIP": 0.43,
    "HYPE": 0.74,
    "BULLCAT": 0.46,
    "MIZUKARA": 0.36,
    "WPLS": 0.36,
    "AKEDO": 0.36,
    "AKE": 0.36,
    "ETHEREUM": 0.36,
    "RUG": 0.36,
    "RHS": 0.36,
    "INK": 0.36,
    "GREENBULL": 0.36,
    "SHX": 0.6,
    "SYN": 0.6,
    "ONDO": 0.6,
    "CRCL": 0.6,
    "US": 0.6,
    "BANK": 0.6,
    "BLB": 0.6,
    "GAYU": 0.6,
    "TENDIES": 1,
    "INJ": 2,
    "GBULL": 1,
    "DOG": 1,
    "SPCX": 1,
    "SPX": 1,
    "LUNC": 1,
    "USTC": 1,
    "DOGE": 1,
    "TRUMP": 1
  },
  "alerted": {
    "SOL": 1784255410
  },
  "updatedAt": 1784255410
}
