{
  "baseline": {
    "BTC": 4.41,
    "HYPE": 1.52,
    "XRP": 1.19,
    "NEAR": 0.59,
    "SOL": 1.25,
    "ETH": 2.21,
    "ADA": 0.56,
    "RIVER": 1.03,
    "ONDO": 0.46,
    "STRC": 0.46,
    "ALTSZN": 0.62,
    "QUIP": 0.62,
    "DTC": 0.36,
    "OTHERS": 0.36,
    "IWM": 0.36,
    "DOGEUS": 0.72,
    "USELESS": 0.36,
    "REKT": 0.36,
    "DOGE": 0.72,
    "BAT": 0.36,
    "FLR": 0.36,
    "STRK": 0.36,
    "IBIT": 0.36,
    "BSOL": 0.36,
    "TONX": 0.36,
    "SUIG": 0.36,
    "TON": 0.36,
    "GGRAM": 0.36,
    "PARK": 0.36,
    "KAS": 0.6,
    "BHYP": 0.6,
    "ZEC": 2.2,
    "MEMECOIN": 0.6,
    "XLM": 0.6,
    "BABYDOGE": 0.6,
    "SERV": 0.6,
    "HBM": 0.6,
    "QNT": 0.6,
    "XDC": 0.6,
    "ALGO": 0.6,
    "FET": 1,
    "DC": 1,
    "WLD": 2,
    "SATUSD": 1
  },
  "alerted": {
    "HYPE": 1780584007,
    "SOL": 1780602988,
    "ZEC": 1780652039
  },
  "updatedAt": 1780652039
}
