{
  "baseline": {
    "BTC": 1.79,
    "XRP": 1.44,
    "ETH": 1.2,
    "ANSEM": 6.11,
    "PUMP": 0.38,
    "SOL": 3.33,
    "TRUMP": 1.08,
    "USELESS": 0.63,
    "FARTCOIN": 0.76,
    "SPCX": 0.41,
    "DOGE": 0.36,
    "FLOKI": 0.36,
    "SHIB": 0.76,
    "BONK": 0.6,
    "ARPA": 0.36,
    "ZANO": 0.36,
    "CASH": 0.36,
    "PENGU": 0.36,
    "NFP": 0.36,
    "LUNA": 0.36,
    "FTT": 0.36,
    "OM": 0.36,
    "SQUID": 0.36,
    "TAC": 0.72,
    "BABYANSEM": 0.6,
    "ZANSEM": 0.76,
    "SHIP": 0.76,
    "MANIFEST": 0.36,
    "PEPE": 1.6,
    "TRIPLET": 0.6,
    "WORMI": 3,
    "LOA": 0.6,
    "CIRC": 0.6,
    "KINS": 0.6,
    "THREE": 0.6,
    "ORBRYN": 0.6,
    "LOKI": 0.6,
    "GOLD": 0.6,
    "SILKAI": 0.6,
    "HUNTER": 0.6,
    "ADA": 0.6,
    "MU": 0.6,
    "TIVA": 0.6,
    "PI": 0.6,
    "DOG": 0.6,
    "WKC": 0.6,
    "RLUSD": 2,
    "HBC": 2,
    "KAS": 1,
    "SHEEP": 1,
    "BOTZ": 1,
    "ROBO": 1,
    "ARKQ": 1,
    "TSLA": 1,
    "AMZN": 1,
    "OUST": 1,
    "SYM": 1,
    "BOT": 1,
    "TTS": 1,
    "QUBIC": 1
  },
  "alerted": {
    "BTC": 1783087231,
    "ANSEM": 1783133127,
    "WORMI": 1783133127
  },
  "updatedAt": 1783171318
}
